inmanta_module_factory/__init__.py
inmanta_module_factory/builder.py
inmanta_module_factory/py.typed
inmanta_module_factory/helpers/__init__.py
inmanta_module_factory/helpers/const.py
inmanta_module_factory/helpers/utils.py
inmanta_module_factory/inmanta/__init__.py
inmanta_module_factory/inmanta/attribute.py
inmanta_module_factory/inmanta/entity.py
inmanta_module_factory/inmanta/entity_field.py
inmanta_module_factory/inmanta/entity_relation.py
inmanta_module_factory/inmanta/implement.py
inmanta_module_factory/inmanta/implementation.py
inmanta_module_factory/inmanta/index.py
inmanta_module_factory/inmanta/module.py
inmanta_module_factory/inmanta/module_element.py
inmanta_module_factory/inmanta/plugin.py
inmanta_module_factory/inmanta/typedef.py
inmanta_module_factory/inmanta/types.py
inmanta_module_factory/inmanta/modules/__init__.py
inmanta_module_factory/inmanta/modules/std.py
inmanta_module_factory/stats/__init__.py
inmanta_module_factory/stats/stats.py
inmanta_module_factory-3.1.0.dist-info/licenses/LICENSE
inmanta_module_factory-3.1.0.dist-info/METADATA
inmanta_module_factory-3.1.0.dist-info/WHEEL
inmanta_module_factory-3.1.0.dist-info/top_level.txt
inmanta_module_factory-3.1.0.dist-info/RECORD
