Metadata-Version: 2.4
Name: inmanta-module-factory
Version: 3.1.0
Summary: Library for building inmanta modules with python code
Author: Inmanta
Author-email: code@inmanta.com
License: Apache 2.0
License-File: LICENSE
Requires-Dist: inmanta-core>=7.0.1
Requires-Dist: PyYAML~=6.0
Requires-Dist: cookiecutter<3.0.0,>=1.7.3
Dynamic: license-file
